{"inkVersion":20,"root":[[{"#":"name Sam"},"^Out of all the days, you have to pick today to go out to centro park?","\n","^It is a light week for both of us.",{"#":"name May"},"\n","^No test, no project,",{"#":"name May"},"\n","^Just a good old spring weekend.",{"#":"name May"},"\n","^We aren’t going to get a lot of those this semester.",{"#":"name May"},"\n","^Ahhh the sun is killing me!",{"#":"name Sam"},"\n",{"->":"Sun_Choice"},["done",{"#f":5,"#n":"g-0"}],null],"done",{"Sun_Choice":[[["ev",{"^->":"Sun_Choice.0.0.$r1"},{"temp=":"$r"},"str",{"->":".^.s"},[{"#n":"$r1"}],"/str","/ev",{"*":".^.^.c-0","flg":18},{"s":["^It is so hot today! ",{"->":"$r","var":true},null]}],["ev",{"^->":"Sun_Choice.0.1.$r1"},{"temp=":"$r"},"str",{"->":".^.s"},[{"#n":"$r1"}],"/str","/ev",{"*":".^.^.c-1","flg":18},{"s":["^You know I am a vampire, right? ",{"->":"$r","var":true},null]}],["ev",{"^->":"Sun_Choice.0.2.$r1"},{"temp=":"$r"},"str",{"->":".^.s"},[{"#n":"$r1"}],"/str","/ev",{"*":".^.^.c-2","flg":18},{"s":["^Wryyy~ ",{"->":"$r","var":true},null]}],{"c-0":["ev",{"^->":"Sun_Choice.0.c-0.$r2"},"/ev",{"temp=":"$r"},{"->":".^.^.0.s"},[{"#n":"$r2"}],"\n",{"->":"Toast"},{"#f":5}],"c-1":["ev",{"^->":"Sun_Choice.0.c-1.$r2"},"/ev",{"temp=":"$r"},{"->":".^.^.1.s"},[{"#n":"$r2"}],"\n",{"->":"Toast"},{"#f":5}],"c-2":["ev",{"^->":"Sun_Choice.0.c-2.$r2"},"/ev",{"temp=":"$r"},{"->":".^.^.2.s"},[{"#n":"$r2"}],"\n",{"->":"Toast"},{"#f":5}]}],{"#f":1}],"Toast":["^I am as dead as a piece of toast bread.",{"#":"name Sam"},"\n","^Yum, I hope you taste as delicious as a fine piece of peanut butter jelly sandwich.",{"#":"name May"},"\n","^Seriously, took your man out to die like that?",{"#":"name Sam"},"\n","^Oh come on, we are in the shade.",{"#":"name May"},"\n","^And I did ask you back in the winter. You said it was so cold that you are going to get your feet frozen.",{"#":"name May"},"\n","^I did.",{"#":"name Sam"},"\n","^I did get my feet frozen.",{"#":"name Sam"},"\n","^I couldn’t feel my feet on our way back last time we went to the dumbo.",{"#":"name Sam"},"\n","^And we walked back to our apartment.",{"#":"name Sam"},"\n","^25 minutes walk!",{"#":"name Sam"},"\n","^I told you it was cold before we left!",{"#":"name May"},"\n","^Yet all your heavy clothes are dead in the box in the walking-in closet for this whole damn New York winter.",{"#":"name May"},"\n","^Why do you only remember the bad stuff!",{"#":"name May"},"\n","^Ah— Waves crashing onto the shore and wind ruffling my ears.",{"#":"name May"},"\n","^It was the best date ever.",{"#":"name May"},"\n",{"->":"Dumbo"},{"#f":1}],"Dumbo":[[["ev",{"^->":"Dumbo.0.0.$r1"},{"temp=":"$r"},"str",{"->":".^.s"},[{"#n":"$r1"}],"/str","/ev",{"*":".^.^.c-0","flg":18},{"s":["^-Roll your eyes-",{"->":"$r","var":true},null]}],["ev",{"^->":"Dumbo.0.1.$r1"},{"temp=":"$r"},"str",{"->":".^.s"},[{"#n":"$r1"}],"/str","/ev",{"*":".^.^.c-1","flg":18},{"s":["^......",{"->":"$r","var":true},null]}],["ev",{"^->":"Dumbo.0.2.$r1"},{"temp=":"$r"},"str",{"->":".^.s"},[{"#n":"$r1"}],"/str","/ev",{"*":".^.^.c-2","flg":18},{"s":["^That’s right",{"->":"$r","var":true},null]}],{"c-0":["ev",{"^->":"Dumbo.0.c-0.$r2"},"/ev",{"temp=":"$r"},{"->":".^.^.0.s"},[{"#n":"$r2"}],"\n",{"->":"Problem"},{"#f":5}],"c-1":["ev",{"^->":"Dumbo.0.c-1.$r2"},"/ev",{"temp=":"$r"},{"->":".^.^.1.s"},[{"#n":"$r2"}],"\n",{"->":"Problem"},{"#f":5}],"c-2":["ev",{"^->":"Dumbo.0.c-2.$r2"},"/ev",{"temp=":"$r"},{"->":".^.^.2.s"},[{"#n":"$r2"}],"\n",{"->":"Problem"},{"#f":5}]}],{"#f":1}],"Problem":["^What? You got a problem?",{"#":"name May"},"\n","^You were wearing a hat!",{"#":"name Sam"},"\n",{"->":"Problem2"},{"#f":1}],"Problem2":["^So what?",{"#":"name May"},"\n","^emm...",{"#":"name Sam"},"\n",{"->":"Hat"},{"#f":1}],"Hat":[["ev","str","^You were beautiful in that hat.","/str","/ev",{"*":".^.c-0","flg":20},"ev","str","^No wind passed through your ears.","/str","/ev",{"*":".^.c-1","flg":20},["ev",{"^->":"Hat.0.12.$r1"},{"temp=":"$r"},"str",{"->":".^.s"},[{"#n":"$r1"}],"/str","/ev",{"*":".^.^.c-2","flg":18},{"s":["^I said you were wearing a hat!",{"->":"$r","var":true},null]}],{"c-0":[{"->":"Beautiful_Hat"},"\n",{"#f":5}],"c-1":[{"->":"No_Wind"},"\n",{"#f":5}],"c-2":["ev",{"^->":"Hat.0.c-2.$r2"},"/ev",{"temp=":"$r"},{"->":".^.^.12.s"},[{"#n":"$r2"}],"\n",{"->":"Problem2"},{"#f":5}]}],{"#f":1}],"Beautiful_Hat":["^I remember us, standing by the shore,",{"#":"name Sam"},"\n","^You leaned on to the wooden rail and closed your eyes,",{"#":"name Sam"},"\n","^You were beautiful in that hat.",{"#":"name Sam"},"\n","^Awww.",{"#":"name May"},"\n",{"->":"Road"},{"#f":1}],"No_Wind":["^There was no wind passing through your ears!",{"#":"name Sam"},"\n","^You were wearing a hat! ",{"#":"name Sam"},"\n","^Those kind with ear flaps!",{"#":"name Sam"},"\n",{"->":"Road"},{"#f":1}],"Road":[["^......",{"#":"name May"},"\n","^......",{"#":"name Sam"},"\n","^Hey are you watching where we are going?",{"#":"name Sam"},"\n","^Eh, no?",{"#":"name May"},"\n","^Then how are we supposed to get out of here?",{"#":"name Sam"},"\n","^What’s the hurry?",{"#":"name May"},"\n","^It's a date.",{"#":"name May"},"\n","^No, I mean how are we going to get out of the park eventually.",{"#":"name Sam"},"\n","^Well we will find a way out eventually.",{"#":"name May"},"\n","^All roads lead to Rome. ",{"#":"name May"},"\n","^and all Romes lead to home.",{"#":"name May"},"\n",["^They lived happily ever after.","\n","end",{"#f":5,"#n":"g-0"}],null],{"#f":1}],"#f":1}],"listDefs":{}}